Metadata-Version: 2.1
Name: hifi-gan-bwe
Version: 0.1.14
Summary: Unofficial implementation of the HiFi-GAN+ model for audio bandwidth extension
Home-page: https://github.com/brentspell/hifi-gan-bwe/
Author: Brent M. Spell
Author-email: brent@brentspell.com
License: UNKNOWN
Platform: UNKNOWN
Classifier: Programming Language :: Python :: 3
Classifier: License :: OSI Approved :: MIT License
Classifier: Operating System :: OS Independent
License-File: LICENSE
